[
    {"image": "./updates/1.png", "link": "news/klinikakan-depq-tunavor-khpipi-virahatakan-buzhum", "title": "Կլինիկական դեպք. թունավոր խպիպի վիրահատական բուժում", "date": "31 Մայիս 2022"},
    {"image": "./updates/2.png", "link": "news/vahanadzev-geghdzi-punktsion-biopsia", "title": "Վահանաձև գեղձի պունկցիոն բիոպսիա", "date": "26 Մայիս 2022"},
    {"image": "./updates/3.png", "link": "news/klinikakan-depq-hamalir-buzhum-artahaytvats-drakan-ardyunqov", "title": "Կլինիկական դեպք. համալիր բուժում՝ արտահայտված դրական արդյունքով", "date": "26 Մայիս 2022"}
]